compressbench/__init__.py
compressbench/benchmark.py
compressbench/cli.py
compressbench/results.py
compressbench/types.py
compressbench/utils.py
compressbench-0.1.0.dist-info/licenses/LICENSE
compressbench-0.1.0.dist-info/METADATA
compressbench-0.1.0.dist-info/WHEEL
compressbench-0.1.0.dist-info/entry_points.txt
compressbench-0.1.0.dist-info/top_level.txt
compressbench-0.1.0.dist-info/RECORD
