Metadata-Version: 2.4
Name: compressbench
Version: 0.1.0
Summary: CLI tool to benchmark compression algorithms on Parquet datasets
Author: Konstantinas Mamonas
License: MIT
Requires-Python: >=3.9
License-File: LICENSE
Requires-Dist: typer
Requires-Dist: pyarrow
Requires-Dist: duckdb
Requires-Dist: python-snappy
Requires-Dist: lz4
Requires-Dist: zstandard
Requires-Dist: seaborn
Provides-Extra: gzip
Provides-Extra: snappy
Requires-Dist: python-snappy; extra == "snappy"
Provides-Extra: lz4
Requires-Dist: lz4; extra == "lz4"
Provides-Extra: zstd
Requires-Dist: zstandard; extra == "zstd"
Provides-Extra: all
Requires-Dist: python-snappy; extra == "all"
Requires-Dist: lz4; extra == "all"
Requires-Dist: zstandard; extra == "all"
Provides-Extra: viz
Requires-Dist: matplotlib; extra == "viz"
Provides-Extra: dev
Requires-Dist: build; extra == "dev"
Requires-Dist: twine; extra == "dev"
Requires-Dist: pytest; extra == "dev"
Requires-Dist: black; extra == "dev"
Requires-Dist: ruff; extra == "dev"
Dynamic: license-file
